textnoise_analyzer/__init__.py
textnoise_analyzer/main.py
textnoise_analyzer/prompts.py
textnoise_analyzer-2025.12.21160634.dist-info/METADATA
textnoise_analyzer-2025.12.21160634.dist-info/WHEEL
textnoise_analyzer-2025.12.21160634.dist-info/top_level.txt
textnoise_analyzer-2025.12.21160634.dist-info/RECORD
