Metadata-Version: 2.4
Name: textnoise-analyzer
Version: 2025.12.21160634
Summary: A new package that helps users determine the noise level of their environment by analyzing text descriptions. Users input a brief text describing their surroundings, and the package processes this inp
Author-email: textnoise-analyzer <hi@eugene.plus>
License: MIT
Project-URL: Homepage, https://github.com/chigwell/textnoise-analyzer
Requires-Python: >=3.9
Requires-Dist: langchain-llm7>=0.0.0
Requires-Dist: llmatch-messages>=0.0.0
Requires-Dist: langchain-core>=0.3.0
